mssqltoolsservice/__init__.py
mssqltoolsservice/bin/Microsoft.Azure.Management.ResourceManager.dll
mssqltoolsservice/bin/Microsoft.Azure.Management.Sql.dll
mssqltoolsservice/bin/Microsoft.CSharp.dll
mssqltoolsservice/bin/Microsoft.Data.Tools.Sql.BatchParser.dll
mssqltoolsservice/bin/Microsoft.DotNet.PlatformAbstractions.dll
mssqltoolsservice/bin/Microsoft.Extensions.DependencyModel.dll
mssqltoolsservice/bin/Microsoft.Rest.ClientRuntime.Azure.dll
mssqltoolsservice/bin/Microsoft.Rest.ClientRuntime.dll
mssqltoolsservice/bin/Microsoft.SqlServer.ConnectionInfo.dll
mssqltoolsservice/bin/Microsoft.SqlServer.Management.Dmf.dll
mssqltoolsservice/bin/Microsoft.SqlServer.Management.Sdk.Sfc.dll
mssqltoolsservice/bin/Microsoft.SqlServer.Management.SmoMetadataProvider.dll
mssqltoolsservice/bin/Microsoft.SqlServer.Management.SqlScriptPublishModel.dll
mssqltoolsservice/bin/Microsoft.SqlServer.Management.XEvent.dll
mssqltoolsservice/bin/Microsoft.SqlServer.Management.XEventDbScoped.dll
mssqltoolsservice/bin/Microsoft.SqlServer.Management.XEventDbScopedEnum.dll
mssqltoolsservice/bin/Microsoft.SqlServer.Management.XEventEnum.dll
mssqltoolsservice/bin/Microsoft.SqlServer.Smo.dll
mssqltoolsservice/bin/Microsoft.SqlServer.SmoExtended.dll
mssqltoolsservice/bin/Microsoft.SqlServer.SqlEnum.dll
mssqltoolsservice/bin/Microsoft.SqlServer.SqlParser.dll
mssqltoolsservice/bin/Microsoft.SqlTools.Hosting.dll
mssqltoolsservice/bin/Microsoft.SqlTools.Hosting.pdb
mssqltoolsservice/bin/Microsoft.SqlTools.ResourceProvider.Core.dll
mssqltoolsservice/bin/Microsoft.SqlTools.ResourceProvider.Core.pdb
mssqltoolsservice/bin/Microsoft.SqlTools.ResourceProvider.DefaultImpl.dll
mssqltoolsservice/bin/Microsoft.SqlTools.ResourceProvider.DefaultImpl.pdb
mssqltoolsservice/bin/Microsoft.VisualBasic.dll
mssqltoolsservice/bin/Microsoft.Win32.Primitives.dll
mssqltoolsservice/bin/Microsoft.Win32.Registry.dll
mssqltoolsservice/bin/MicrosoftSqlToolsCredentials
mssqltoolsservice_Linux_64-1.0.0a21.dist-info/DESCRIPTION.rst
mssqltoolsservice_Linux_64-1.0.0a21.dist-info/LICENSE.txt
mssqltoolsservice_Linux_64-1.0.0a21.dist-info/METADATA
mssqltoolsservice_Linux_64-1.0.0a21.dist-info/RECORD
mssqltoolsservice_Linux_64-1.0.0a21.dist-info/WHEEL
mssqltoolsservice_Linux_64-1.0.0a21.dist-info/metadata.json
mssqltoolsservice_Linux_64-1.0.0a21.dist-info/top_level.txt
mssqltoolsservice_Linux_64-1.0.0a21.dist-info/zip-safe
